setup.py
netapp/__init__.py
netapp.santricity.egg-info/PKG-INFO
netapp.santricity.egg-info/SOURCES.txt
netapp.santricity.egg-info/dependency_links.txt
netapp.santricity.egg-info/requires.txt
netapp.santricity.egg-info/top_level.txt
netapp/santricity/__init__.py
netapp/santricity/api_client.py
netapp/santricity/configuration.py
netapp/santricity/rest.py
netapp/santricity/api/__init__.py
netapp/santricity/api/symbol/__init__.py
netapp/santricity/api/symbol/a_api.py
netapp/santricity/api/symbol/b_api.py
netapp/santricity/api/symbol/c_api.py
netapp/santricity/api/symbol/d_api.py
netapp/santricity/api/symbol/e_api.py
netapp/santricity/api/symbol/f_api.py
netapp/santricity/api/symbol/g_api.py
netapp/santricity/api/symbol/i_api.py
netapp/santricity/api/symbol/l_api.py
netapp/santricity/api/symbol/m_api.py
netapp/santricity/api/symbol/p_api.py
netapp/santricity/api/symbol/q_api.py
netapp/santricity/api/symbol/r_api.py
netapp/santricity/api/symbol/s_api.py
netapp/santricity/api/symbol/t_api.py
netapp/santricity/api/symbol/u_api.py
netapp/santricity/api/symbol/v_api.py
netapp/santricity/api/symbol/w_api.py
netapp/santricity/api/utils/__init__.py
netapp/santricity/api/utils/about_api.py
netapp/santricity/api/utils/build_info_api.py
netapp/santricity/api/utils/login_api.py
netapp/santricity/api/v2/__init__.py
netapp/santricity/api/v2/administration_api.py
netapp/santricity/api/v2/configuration_api.py
netapp/santricity/api/v2/copy_services_api.py
netapp/santricity/api/v2/device_asup_api.py
netapp/santricity/api/v2/diagnostics_api.py
netapp/santricity/api/v2/drive_firmware_api.py
netapp/santricity/api/v2/file_management_api.py
netapp/santricity/api/v2/firmware_api.py
netapp/santricity/api/v2/flash_cache_api.py
netapp/santricity/api/v2/hardware_api.py
netapp/santricity/api/v2/mapping_api.py
netapp/santricity/api/v2/mirroring_api.py
netapp/santricity/api/v2/monitoring_api.py
netapp/santricity/api/v2/service_catalog_api.py
netapp/santricity/api/v2/statistics_api.py
netapp/santricity/api/v2/storage_systems_api.py
netapp/santricity/api/v2/upgrade_api.py
netapp/santricity/api/v2/volumes_api.py
netapp/santricity/api/v2/workloads_api.py
netapp/santricity/models/__init__.py
