Metadata-Version: 1.0
Name: netapp.santricity
Version: 1.0
Summary: Python SDK for accessing NetApp Santricity Web Services
Home-page: https://github.com/NetApp/santricity-webapi-pythonsdk
Author: NetApp
Author-email: ng-hsg-engcustomer-esolutions-support@netapp.com
License: The Clear BSD License
Keywords: Swagger,NetApp,Santricity
Platform: UNKNOWN
